LICENSE
MANIFEST.in
README.md
setup.py
sahfqgbwmy/__init__.py
sahfqgbwmy/api_helper.py
sahfqgbwmy/configuration.py
sahfqgbwmy/decorators.py
sahfqgbwmy/sahfqgbwmy_client.py
sahfqgbwmy.egg-info/PKG-INFO
sahfqgbwmy.egg-info/SOURCES.txt
sahfqgbwmy.egg-info/dependency_links.txt
sahfqgbwmy.egg-info/requires.txt
sahfqgbwmy.egg-info/top_level.txt
sahfqgbwmy/controllers/__init__.py
sahfqgbwmy/controllers/api_controller.py
sahfqgbwmy/controllers/base_controller.py
sahfqgbwmy/exceptions/__init__.py
sahfqgbwmy/exceptions/api_exception.py
sahfqgbwmy/http/__init__.py
sahfqgbwmy/http/http_call_back.py
sahfqgbwmy/http/http_client.py
sahfqgbwmy/http/http_context.py
sahfqgbwmy/http/http_method_enum.py
sahfqgbwmy/http/http_request.py
sahfqgbwmy/http/http_response.py
sahfqgbwmy/http/requests_client.py
sahfqgbwmy/http/auth/__init__.py
sahfqgbwmy/http/auth/basic_auth.py
sahfqgbwmy/models/__init__.py
sahfqgbwmy/models/suite_code_enum.py
tests/__init__.py
tests/http_response_catcher.py
tests/test_helper.py
tests/controllers/__init__.py
tests/controllers/controller_test_base.py
tests/controllers/test_api_controller.py